pyhvac/__main__.py
pyhvac/_irhvac.so
pyhvac/irhvac.py
pyhvac/__init__.py
pyhvac/plugins/argo.py
pyhvac/plugins/leberg.py
pyhvac/plugins/kaysun.py
pyhvac/plugins/frigidaire.py
pyhvac/plugins/hvaclib.py
pyhvac/plugins/aux.py
pyhvac/plugins/ge.py
pyhvac/plugins/amcor.py
pyhvac/plugins/kelvinator.py
pyhvac/plugins/hitachi.py
pyhvac/plugins/whirlpool.py
pyhvac/plugins/carrier.py
pyhvac/plugins/sanyo.py
pyhvac/plugins/cooper_hunter.py
pyhvac/plugins/centek.py
pyhvac/plugins/mitsubishi_heavy_industries.py
pyhvac/plugins/subtropic.py
pyhvac/plugins/trotech.py
pyhvac/plugins/goodweather.py
pyhvac/plugins/tokio.py
pyhvac/plugins/technibel.py
pyhvac/plugins/midea.py
pyhvac/plugins/mrcool.py
pyhvac/plugins/sharp.py
pyhvac/plugins/lg.py
pyhvac/plugins/tronitechnik.py
pyhvac/plugins/beko.py
pyhvac/plugins/amana.py
pyhvac/plugins/bosch.py
pyhvac/plugins/danby.py
pyhvac/plugins/kelon.py
pyhvac/plugins/keystone.py
pyhvac/plugins/electra.py
pyhvac/plugins/samsung.py
pyhvac/plugins/delonghi.py
pyhvac/plugins/green.py
pyhvac/plugins/mirage.py
pyhvac/plugins/pioneer_system.py
pyhvac/plugins/kastron.py
pyhvac/plugins/airton.py
pyhvac/plugins/maxell.py
pyhvac/plugins/daikin.py
pyhvac/plugins/neoclima.py
pyhvac/plugins/aeg.py
pyhvac/plugins/voltas.py
pyhvac/plugins/ecoclim.py
pyhvac/plugins/ultimate.py
pyhvac/plugins/gree.py
pyhvac/plugins/truma.py
pyhvac/plugins/panasonic.py
pyhvac/plugins/toshiba.py
pyhvac/plugins/technopoint.py
pyhvac/plugins/comfee.py
pyhvac/plugins/rhoss.py
pyhvac/plugins/daewoo.py
pyhvac/plugins/haier.py
pyhvac/plugins/corona.py
pyhvac/plugins/vailland.py
pyhvac/plugins/coolix.py
pyhvac/plugins/airwell.py
pyhvac/plugins/tcl.py
pyhvac/plugins/teco.py
pyhvac/plugins/fujitsu.py
pyhvac/plugins/soleus.py
pyhvac/plugins/mitsubishi_electric.py
pyhvac/plugins/alaska.py
pyhvac/plugins/vestel.py
pyhvac/plugins/rusclimate.py
pyhvac/plugins/transcold.py
pyhvac/plugins/lennox.py
pyhvac/plugins/mabe.py
pyhvac-0.1.2.dist-info/LICENSE
pyhvac-0.1.2.dist-info/RECORD
pyhvac-0.1.2.dist-info/METADATA
pyhvac-0.1.2.dist-info/top_level.txt
pyhvac-0.1.2.dist-info/entry_points.txt
pyhvac-0.1.2.dist-info/WHEEL
