Metadata-Version: 2.1
Name: pyhvac
Version: 0.1.2
Summary: Python liberary/Utility to generate A/C IR signals
Home-page: http://github.com/frawau/pyhvac
Author: François Wautier
Author-email: francois@wautier.eu
License: UNKNOWN
Platform: UNKNOWN
Classifier: License :: OSI Approved :: MIT License
Classifier: Programming Language :: Python :: 3
Classifier: Programming Language :: Python :: 3.10
Classifier: Programming Language :: Python :: 3.11
Classifier: Programming Language :: Python :: 3.12
License-File: LICENSE
